Metadata-Version: 2.1
Name: html-testRunner-df
Version: 1.2.2.dev4
Summary: A Test Runner in python, for Human Readable HTML Reports
Home-page: https://github.com/dongfangtianyu/HtmlTestRunner
Author: dongfangtianyu
License: MIT license
Keywords: HtmlTestRunner TestRunner Html Reports
Platform: UNKNOWN
Classifier: Development Status :: 4 - Beta
Classifier: Intended Audience :: Developers
Classifier: License :: OSI Approved :: MIT License
Classifier: Natural Language :: English
Classifier: Programming Language :: Python :: 3.9
License-File: LICENSE
License-File: AUTHORS.md
